django_webtest/__init__.py
django_webtest/backends.py
django_webtest/compat.py
django_webtest/middleware.py
django_webtest/pytest_plugin.py
django_webtest/response.py
django_webtest/rest_framework_auth.py
django_webtest-1.9.13.dist-info/AUTHORS.txt
django_webtest-1.9.13.dist-info/LICENSE.txt
django_webtest-1.9.13.dist-info/METADATA
django_webtest-1.9.13.dist-info/WHEEL
django_webtest-1.9.13.dist-info/entry_points.txt
django_webtest-1.9.13.dist-info/top_level.txt
django_webtest-1.9.13.dist-info/RECORD
