Metadata-Version: 2.1
Name: django-webtest
Version: 1.9.13
Summary: Instant integration of Ian Bicking's WebTest (http://docs.pylonsproject.org/projects/webtest/) with Django's testing framework.
Home-page: https://github.com/django-webtest/django-webtest
Author: Mikhail Korobov
Author-email: kmike84@gmail.com
License: MIT license
Project-URL: Code, https://github.com/django-webtest/django-webtest
Project-URL: Issue Tracker, https://github.com/django-webtest/django-webtest/issues
Project-URL: Changelog, https://github.com/django-webtest/django-webtest/blob/master/CHANGES.rst
Keywords: django,webtest,pytest
Classifier: Development Status :: 5 - Production/Stable
Classifier: Environment :: Web Environment
Classifier: Framework :: Django
Classifier: Framework :: Django :: 4.2
Classifier: Framework :: Django :: 5.0
Classifier: Framework :: Django :: 5.1
Classifier: Framework :: Django :: 5.2
Classifier: Intended Audience :: Developers
Classifier: License :: OSI Approved :: MIT License
Classifier: Programming Language :: Python
Classifier: Programming Language :: Python :: 3
Classifier: Programming Language :: Python :: 3.9
Classifier: Programming Language :: Python :: 3.10
Classifier: Programming Language :: Python :: 3.11
Classifier: Programming Language :: Python :: 3.12
Classifier: Programming Language :: Python :: Implementation :: CPython
Classifier: Programming Language :: Python :: Implementation :: PyPy
Classifier: Topic :: Software Development :: Libraries :: Python Modules
Classifier: Topic :: Software Development :: Testing
License-File: LICENSE.txt
License-File: AUTHORS.txt
Requires-Dist: webtest >=1.3.3
